{"name": "10", "Objects": [{"Length": "100", "Height": "100", "Depth": "100", "Stock": null, "Cost": 1000000}], "Items": [{"Length": "67", "Height": "76", "Depth": "42", "Demand": 1, "DemandMax": null, "Value": 213864}, {"Length": "49", "Height": "34", "Depth": "23", "Demand": 1, "DemandMax": null, "Value": 38318}, {"Length": "31", "Height": "27", "Depth": "22", "Demand": 1, "DemandMax": null, "Value": 18414}, {"Length": "49", "Height": "43", "Depth": "11", "Demand": 1, "DemandMax": null, "Value": 23177}, {"Length": "12", "Height": "23", "Depth": "10", "Demand": 1, "DemandMax": null, "Value": 2760}, {"Length": "38", "Height": "14", "Depth": "20", "Demand": 1, "DemandMax": null, "Value": 10640}, {"Length": "30", "Height": "29", "Depth": "43", "Demand": 1, "DemandMax": null, "Value": 37410}, {"Length": "98", "Height": "94", "Depth": "93", "Demand": 1, "DemandMax": null, "Value": 856716}, {"Length": "9", "Height": "45", "Depth": "21", "Demand": 1, "DemandMax": null, "Value": 8505}, {"Length": "51", "Height": "84", "Depth": "64", "Demand": 1, "DemandMax": null, "Value": 274176}, {"Length": "17", "Height": "15", "Depth": "30", "Demand": 1, "DemandMax": null, "Value": 7650}, {"Length": "1", "Height": "18", "Depth": "19", "Demand": 1, "DemandMax": null, "Value": 342}, {"Length": "6", "Height": "37", "Depth": "30", "Demand": 1, "DemandMax": null, "Value": 6660}, {"Length": "37", "Height": "45", "Depth": "11", "Demand": 1, "DemandMax": null, "Value": 18315}, {"Length": "95", "Height": "89", "Depth": "50", "Demand": 1, "DemandMax": null, "Value": 422750}, {"Length": "46", "Height": "25", "Depth": "21", "Demand": 1, "DemandMax": null, "Value": 24150}, {"Length": "92", "Height": "91", "Depth": "12", "Demand": 1, "DemandMax": null, "Value": 100464}, {"Length": "13", "Height": "48", "Depth": "26", "Demand": 1, "DemandMax": null, "Value": 16224}, {"Length": "44", "Height": "22", "Depth": "48", "Demand": 1, "DemandMax": null, "Value": 46464}, {"Length": "46", "Height": "6", "Depth": "25", "Demand": 1, "DemandMax": null, "Value": 6900}, {"Length": "90", "Height": "94", "Depth": "86", "Demand": 1, "DemandMax": null, "Value": 727560}, {"Length": "15", "Height": "82", "Depth": "94", "Demand": 1, "DemandMax": null, "Value": 115620}, {"Length": "76", "Height": "68", "Depth": "68", "Demand": 1, "DemandMax": null, "Value": 351424}, {"Length": "42", "Height": "81", "Depth": "96", "Demand": 1, "DemandMax": null, "Value": 326592}, {"Length": "14", "Height": "29", "Depth": "11", "Demand": 1, "DemandMax": null, "Value": 4466}, {"Length": "46", "Height": "7", "Depth": "2", "Demand": 1, "DemandMax": null, "Value": 644}, {"Length": "4", "Height": "35", "Depth": "50", "Demand": 1, "DemandMax": null, "Value": 7000}, {"Length": "39", "Height": "33", "Depth": "7", "Demand": 1, "DemandMax": null, "Value": 9009}, {"Length": "18", "Height": "24", "Depth": "47", "Demand": 1, "DemandMax": null, "Value": 20304}, {"Length": "5", "Height": "13", "Depth": "24", "Demand": 1, "DemandMax": null, "Value": 1560}, {"Length": "98", "Height": "4", "Depth": "89", "Demand": 1, "DemandMax": null, "Value": 34888}, {"Length": "88", "Height": "73", "Depth": "27", "Demand": 1, "DemandMax": null, "Value": 173448}, {"Length": "20", "Height": "73", "Depth": "74", "Demand": 1, "DemandMax": null, "Value": 108040}, {"Length": "48", "Height": "24", "Depth": "11", "Demand": 1, "DemandMax": null, "Value": 12672}, {"Length": "8", "Height": "7", "Depth": "27", "Demand": 1, "DemandMax": null, "Value": 1512}, {"Length": "20", "Height": "5", "Depth": "14", "Demand": 1, "DemandMax": null, "Value": 1400}, {"Length": "24", "Height": "46", "Depth": "49", "Demand": 1, "DemandMax": null, "Value": 54096}, {"Length": "94", "Height": "92", "Depth": "3", "Demand": 1, "DemandMax": null, "Value": 25944}, {"Length": "41", "Height": "48", "Depth": "38", "Demand": 1, "DemandMax": null, "Value": 74784}, {"Length": "27", "Height": "28", "Depth": "35", "Demand": 1, "DemandMax": null, "Value": 26460}, {"Length": "22", "Height": "93", "Depth": "80", "Demand": 1, "DemandMax": null, "Value": 163680}, {"Length": "27", "Height": "11", "Depth": "29", "Demand": 1, "DemandMax": null, "Value": 8613}, {"Length": "30", "Height": "91", "Depth": "88", "Demand": 1, "DemandMax": null, "Value": 240240}, {"Length": "91", "Height": "87", "Depth": "26", "Demand": 1, "DemandMax": null, "Value": 205842}, {"Length": "39", "Height": "2", "Depth": "36", "Demand": 1, "DemandMax": null, "Value": 2808}, {"Length": "97", "Height": "34", "Depth": "76", "Demand": 1, "DemandMax": null, "Value": 250648}, {"Length": "45", "Height": "33", "Depth": "24", "Demand": 1, "DemandMax": null, "Value": 35640}, {"Length": "19", "Height": "48", "Depth": "16", "Demand": 1, "DemandMax": null, "Value": 14592}, {"Length": "38", "Height": "2", "Depth": "43", "Demand": 1, "DemandMax": null, "Value": 3268}, {"Length": "42", "Height": "29", "Depth": "22", "Demand": 1, "DemandMax": null, "Value": 26796}, {"Length": "84", "Height": "41", "Depth": "82", "Demand": 1, "DemandMax": null, "Value": 282408}, {"Length": "4", "Height": "73", "Depth": "86", "Demand": 1, "DemandMax": null, "Value": 25112}, {"Length": "36", "Height": "33", "Depth": "10", "Demand": 1, "DemandMax": null, "Value": 11880}, {"Length": "80", "Height": "83", "Depth": "62", "Demand": 1, "DemandMax": null, "Value": 411680}, {"Length": "3", "Height": "10", "Depth": "26", "Demand": 1, "DemandMax": null, "Value": 780}, {"Length": "66", "Height": "59", "Depth": "69", "Demand": 1, "DemandMax": null, "Value": 268686}, {"Length": "45", "Height": "44", "Depth": "41", "Demand": 1, "DemandMax": null, "Value": 81180}, {"Length": "35", "Height": "34", "Depth": "50", "Demand": 1, "DemandMax": null, "Value": 59500}, {"Length": "6", "Height": "20", "Depth": "38", "Demand": 1, "DemandMax": null, "Value": 4560}, {"Length": "47", "Height": "8", "Depth": "48", "Demand": 1, "DemandMax": null, "Value": 18048}, {"Length": "91", "Height": "100", "Depth": "16", "Demand": 1, "DemandMax": null, "Value": 145600}, {"Length": "98", "Height": "72", "Depth": "2", "Demand": 1, "DemandMax": null, "Value": 14112}, {"Length": "55", "Height": "98", "Depth": "96", "Demand": 1, "DemandMax": null, "Value": 517440}, {"Length": "42", "Height": "66", "Depth": "83", "Demand": 1, "DemandMax": null, "Value": 230076}, {"Length": "67", "Height": "20", "Depth": "83", "Demand": 1, "DemandMax": null, "Value": 111220}, {"Length": "22", "Height": "44", "Depth": "6", "Demand": 1, "DemandMax": null, "Value": 5808}, {"Length": "9", "Height": "23", "Depth": "40", "Demand": 1, "DemandMax": null, "Value": 8280}, {"Length": "83", "Height": "51", "Depth": "55", "Demand": 1, "DemandMax": null, "Value": 232815}, {"Length": "73", "Height": "91", "Depth": "67", "Demand": 1, "DemandMax": null, "Value": 445081}, {"Length": "18", "Height": "25", "Depth": "33", "Demand": 1, "DemandMax": null, "Value": 14850}, {"Length": "17", "Height": "20", "Depth": "46", "Demand": 1, "DemandMax": null, "Value": 15640}, {"Length": "47", "Height": "48", "Depth": "47", "Demand": 1, "DemandMax": null, "Value": 106032}, {"Length": "39", "Height": "25", "Depth": "34", "Demand": 1, "DemandMax": null, "Value": 33150}, {"Length": "6", "Height": "34", "Depth": "18", "Demand": 1, "DemandMax": null, "Value": 3672}, {"Length": "90", "Height": "47", "Depth": "66", "Demand": 1, "DemandMax": null, "Value": 279180}, {"Length": "92", "Height": "77", "Depth": "75", "Demand": 1, "DemandMax": null, "Value": 531300}, {"Length": "82", "Height": "79", "Depth": "27", "Demand": 1, "DemandMax": null, "Value": 174906}, {"Length": "50", "Height": "5", "Depth": "31", "Demand": 1, "DemandMax": null, "Value": 7750}, {"Length": "5", "Height": "40", "Depth": "2", "Demand": 1, "DemandMax": null, "Value": 400}, {"Length": "21", "Height": "74", "Depth": "98", "Demand": 1, "DemandMax": null, "Value": 152292}, {"Length": "98", "Height": "65", "Depth": "99", "Demand": 1, "DemandMax": null, "Value": 630630}, {"Length": "21", "Height": "29", "Depth": "28", "Demand": 1, "DemandMax": null, "Value": 17052}, {"Length": "8", "Height": "49", "Depth": "40", "Demand": 1, "DemandMax": null, "Value": 15680}, {"Length": "24", "Height": "43", "Depth": "35", "Demand": 1, "DemandMax": null, "Value": 36120}, {"Length": "7", "Height": "38", "Depth": "48", "Demand": 1, "DemandMax": null, "Value": 12768}, {"Length": "40", "Height": "27", "Depth": "3", "Demand": 1, "DemandMax": null, "Value": 3240}, {"Length": "43", "Height": "7", "Depth": "9", "Demand": 1, "DemandMax": null, "Value": 2709}, {"Length": "48", "Height": "40", "Depth": "31", "Demand": 1, "DemandMax": null, "Value": 59520}, {"Length": "69", "Height": "75", "Depth": "45", "Demand": 1, "DemandMax": null, "Value": 232875}, {"Length": "17", "Height": "1", "Depth": "4", "Demand": 1, "DemandMax": null, "Value": 68}, {"Length": "6", "Height": "30", "Depth": "13", "Demand": 1, "DemandMax": null, "Value": 2340}, {"Length": "32", "Height": "45", "Depth": "2", "Demand": 1, "DemandMax": null, "Value": 2880}, {"Length": "30", "Height": "40", "Depth": "41", "Demand": 1, "DemandMax": null, "Value": 49200}, {"Length": "71", "Height": "91", "Depth": "21", "Demand": 1, "DemandMax": null, "Value": 135681}, {"Length": "33", "Height": "30", "Depth": "44", "Demand": 1, "DemandMax": null, "Value": 43560}, {"Length": "89", "Height": "77", "Depth": "45", "Demand": 1, "DemandMax": null, "Value": 308385}, {"Length": "15", "Height": "35", "Depth": "3", "Demand": 1, "DemandMax": null, "Value": 1575}, {"Length": "31", "Height": "45", "Depth": "19", "Demand": 1, "DemandMax": null, "Value": 26505}, {"Length": "42", "Height": "9", "Depth": "11", "Demand": 1, "DemandMax": null, "Value": 4158}, {"Length": "72", "Height": "28", "Depth": "68", "Demand": 1, "DemandMax": null, "Value": 137088}, {"Length": "7", "Height": "34", "Depth": "13", "Demand": 1, "DemandMax": null, "Value": 3094}, {"Length": "66", "Height": "6", "Depth": "78", "Demand": 1, "DemandMax": null, "Value": 30888}, {"Length": "25", "Height": "28", "Depth": "14", "Demand": 1, "DemandMax": null, "Value": 9800}, {"Length": "32", "Height": "70", "Depth": "76", "Demand": 1, "DemandMax": null, "Value": 170240}, {"Length": "86", "Height": "4", "Depth": "94", "Demand": 1, "DemandMax": null, "Value": 32336}, {"Length": "26", "Height": "11", "Depth": "10", "Demand": 1, "DemandMax": null, "Value": 2860}, {"Length": "2", "Height": "32", "Depth": "24", "Demand": 1, "DemandMax": null, "Value": 1536}, {"Length": "96", "Height": "89", "Depth": "22", "Demand": 1, "DemandMax": null, "Value": 187968}, {"Length": "36", "Height": "3", "Depth": "48", "Demand": 1, "DemandMax": null, "Value": 5184}, {"Length": "76", "Height": "94", "Depth": "79", "Demand": 1, "DemandMax": null, "Value": 564376}, {"Length": "27", "Height": "84", "Depth": "86", "Demand": 1, "DemandMax": null, "Value": 195048}, {"Length": "49", "Height": "49", "Depth": "14", "Demand": 1, "DemandMax": null, "Value": 33614}, {"Length": "91", "Height": "82", "Depth": "31", "Demand": 1, "DemandMax": null, "Value": 231322}, {"Length": "97", "Height": "94", "Depth": "100", "Demand": 1, "DemandMax": null, "Value": 911800}, {"Length": "2", "Height": "22", "Depth": "28", "Demand": 1, "DemandMax": null, "Value": 1232}, {"Length": "15", "Height": "27", "Depth": "20", "Demand": 1, "DemandMax": null, "Value": 8100}, {"Length": "19", "Height": "13", "Depth": "35", "Demand": 1, "DemandMax": null, "Value": 8645}, {"Length": "78", "Height": "17", "Depth": "69", "Demand": 1, "DemandMax": null, "Value": 91494}, {"Length": "48", "Height": "26", "Depth": "36", "Demand": 1, "DemandMax": null, "Value": 44928}, {"Length": "86", "Height": "16", "Depth": "91", "Demand": 1, "DemandMax": null, "Value": 125216}, {"Length": "71", "Height": "14", "Depth": "75", "Demand": 1, "DemandMax": null, "Value": 74550}, {"Length": "47", "Height": "46", "Depth": "7", "Demand": 1, "DemandMax": null, "Value": 15134}, {"Length": "45", "Height": "48", "Depth": "25", "Demand": 1, "DemandMax": null, "Value": 54000}, {"Length": "96", "Height": "68", "Depth": "26", "Demand": 1, "DemandMax": null, "Value": 169728}, {"Length": "40", "Height": "35", "Depth": "33", "Demand": 1, "DemandMax": null, "Value": 46200}, {"Length": "25", "Height": "28", "Depth": "45", "Demand": 1, "DemandMax": null, "Value": 31500}, {"Length": "70", "Height": "5", "Depth": "84", "Demand": 1, "DemandMax": null, "Value": 29400}, {"Length": "40", "Height": "16", "Depth": "30", "Demand": 1, "DemandMax": null, "Value": 19200}, {"Length": "41", "Height": "33", "Depth": "41", "Demand": 1, "DemandMax": null, "Value": 55473}, {"Length": "10", "Height": "36", "Depth": "26", "Demand": 1, "DemandMax": null, "Value": 9360}, {"Length": "32", "Height": "2", "Depth": "13", "Demand": 1, "DemandMax": null, "Value": 832}, {"Length": "49", "Height": "46", "Depth": "45", "Demand": 1, "DemandMax": null, "Value": 101430}, {"Length": "93", "Height": "3", "Depth": "71", "Demand": 1, "DemandMax": null, "Value": 19809}, {"Length": "9", "Height": "11", "Depth": "38", "Demand": 1, "DemandMax": null, "Value": 3762}, {"Length": "78", "Height": "6", "Depth": "97", "Demand": 1, "DemandMax": null, "Value": 45396}, {"Length": "17", "Height": "18", "Depth": "42", "Demand": 1, "DemandMax": null, "Value": 12852}, {"Length": "90", "Height": "67", "Depth": "32", "Demand": 1, "DemandMax": null, "Value": 192960}, {"Length": "11", "Height": "17", "Depth": "32", "Demand": 1, "DemandMax": null, "Value": 5984}, {"Length": "15", "Height": "41", "Depth": "16", "Demand": 1, "DemandMax": null, "Value": 9840}, {"Length": "28", "Height": "35", "Depth": "48", "Demand": 1, "DemandMax": null, "Value": 47040}, {"Length": "81", "Height": "89", "Depth": "70", "Demand": 1, "DemandMax": null, "Value": 504630}, {"Length": "20", "Height": "24", "Depth": "6", "Demand": 1, "DemandMax": null, "Value": 2880}, {"Length": "32", "Height": "42", "Depth": "17", "Demand": 1, "DemandMax": null, "Value": 22848}, {"Length": "31", "Height": "20", "Depth": "18", "Demand": 1, "DemandMax": null, "Value": 11160}, {"Length": "70", "Height": "32", "Depth": "88", "Demand": 1, "DemandMax": null, "Value": 197120}, {"Length": "44", "Height": "25", "Depth": "26", "Demand": 1, "DemandMax": null, "Value": 28600}, {"Length": "37", "Height": "29", "Depth": "10", "Demand": 1, "DemandMax": null, "Value": 10730}, {"Length": "3", "Height": "22", "Depth": "6", "Demand": 1, "DemandMax": null, "Value": 396}, {"Length": "14", "Height": "47", "Depth": "48", "Demand": 1, "DemandMax": null, "Value": 31584}, {"Length": "4", "Height": "93", "Depth": "74", "Demand": 1, "DemandMax": null, "Value": 27528}]}