{"name": "9", "Objects": [{"Length": "100", "Height": "100", "Depth": "100", "Stock": null, "Cost": 1000000}], "Items": [{"Length": "70", "Height": "49", "Depth": "87", "Demand": 1, "DemandMax": null, "Value": 298410}, {"Length": "45", "Height": "82", "Depth": "97", "Demand": 1, "DemandMax": null, "Value": 357930}, {"Length": "22", "Height": "68", "Depth": "78", "Demand": 1, "DemandMax": null, "Value": 116688}, {"Length": "86", "Height": "30", "Depth": "69", "Demand": 1, "DemandMax": null, "Value": 178020}, {"Length": "64", "Height": "89", "Depth": "71", "Demand": 1, "DemandMax": null, "Value": 404416}, {"Length": "86", "Height": "76", "Depth": "94", "Demand": 1, "DemandMax": null, "Value": 614384}, {"Length": "74", "Height": "77", "Depth": "49", "Demand": 1, "DemandMax": null, "Value": 279202}, {"Length": "69", "Height": "39", "Depth": "96", "Demand": 1, "DemandMax": null, "Value": 258336}, {"Length": "73", "Height": "31", "Depth": "80", "Demand": 1, "DemandMax": null, "Value": 181040}, {"Length": "60", "Height": "92", "Depth": "60", "Demand": 1, "DemandMax": null, "Value": 331200}, {"Length": "87", "Height": "4", "Depth": "86", "Demand": 1, "DemandMax": null, "Value": 29928}, {"Length": "99", "Height": "11", "Depth": "75", "Demand": 1, "DemandMax": null, "Value": 81675}, {"Length": "80", "Height": "43", "Depth": "99", "Demand": 1, "DemandMax": null, "Value": 340560}, {"Length": "79", "Height": "84", "Depth": "10", "Demand": 1, "DemandMax": null, "Value": 66360}, {"Length": "92", "Height": "44", "Depth": "80", "Demand": 1, "DemandMax": null, "Value": 323840}, {"Length": "85", "Height": "2", "Depth": "78", "Demand": 1, "DemandMax": null, "Value": 13260}, {"Length": "96", "Height": "18", "Depth": "84", "Demand": 1, "DemandMax": null, "Value": 145152}, {"Length": "97", "Height": "46", "Depth": "73", "Demand": 1, "DemandMax": null, "Value": 325726}, {"Length": "85", "Height": "39", "Depth": "87", "Demand": 1, "DemandMax": null, "Value": 288405}, {"Length": "73", "Height": "72", "Depth": "4", "Demand": 1, "DemandMax": null, "Value": 21024}, {"Length": "68", "Height": "2", "Depth": "94", "Demand": 1, "DemandMax": null, "Value": 12784}, {"Length": "83", "Height": "83", "Depth": "10", "Demand": 1, "DemandMax": null, "Value": 68890}, {"Length": "69", "Height": "27", "Depth": "95", "Demand": 1, "DemandMax": null, "Value": 176985}, {"Length": "88", "Height": "30", "Depth": "74", "Demand": 1, "DemandMax": null, "Value": 195360}, {"Length": "72", "Height": "35", "Depth": "94", "Demand": 1, "DemandMax": null, "Value": 236880}, {"Length": "95", "Height": "89", "Depth": "5", "Demand": 1, "DemandMax": null, "Value": 42275}, {"Length": "99", "Height": "75", "Depth": "52", "Demand": 1, "DemandMax": null, "Value": 386100}, {"Length": "80", "Height": "50", "Depth": "86", "Demand": 1, "DemandMax": null, "Value": 344000}, {"Length": "76", "Height": "15", "Depth": "96", "Demand": 1, "DemandMax": null, "Value": 109440}, {"Length": "68", "Height": "45", "Depth": "70", "Demand": 1, "DemandMax": null, "Value": 214200}, {"Length": "70", "Height": "67", "Depth": "9", "Demand": 1, "DemandMax": null, "Value": 42210}, {"Length": "74", "Height": "41", "Depth": "95", "Demand": 1, "DemandMax": null, "Value": 288230}, {"Length": "97", "Height": "19", "Depth": "100", "Demand": 1, "DemandMax": null, "Value": 184300}, {"Length": "20", "Height": "92", "Depth": "66", "Demand": 1, "DemandMax": null, "Value": 121440}, {"Length": "79", "Height": "36", "Depth": "78", "Demand": 1, "DemandMax": null, "Value": 221832}, {"Length": "81", "Height": "8", "Depth": "95", "Demand": 1, "DemandMax": null, "Value": 61560}, {"Length": "89", "Height": "28", "Depth": "80", "Demand": 1, "DemandMax": null, "Value": 199360}, {"Length": "57", "Height": "100", "Depth": "97", "Demand": 1, "DemandMax": null, "Value": 552900}, {"Length": "25", "Height": "22", "Depth": "12", "Demand": 1, "DemandMax": null, "Value": 6600}, {"Length": "81", "Height": "9", "Depth": "93", "Demand": 1, "DemandMax": null, "Value": 67797}, {"Length": "89", "Height": "98", "Depth": "81", "Demand": 1, "DemandMax": null, "Value": 706482}, {"Length": "97", "Height": "100", "Depth": "37", "Demand": 1, "DemandMax": null, "Value": 358900}, {"Length": "77", "Height": "20", "Depth": "88", "Demand": 1, "DemandMax": null, "Value": 135520}, {"Length": "77", "Height": "3", "Depth": "78", "Demand": 1, "DemandMax": null, "Value": 18018}, {"Length": "91", "Height": "38", "Depth": "82", "Demand": 1, "DemandMax": null, "Value": 283556}, {"Length": "84", "Height": "31", "Depth": "68", "Demand": 1, "DemandMax": null, "Value": 177072}, {"Length": "46", "Height": "95", "Depth": "95", "Demand": 1, "DemandMax": null, "Value": 415150}, {"Length": "67", "Height": "38", "Depth": "83", "Demand": 1, "DemandMax": null, "Value": 211318}, {"Length": "76", "Height": "29", "Depth": "81", "Demand": 1, "DemandMax": null, "Value": 178524}, {"Length": "43", "Height": "41", "Depth": "31", "Demand": 1, "DemandMax": null, "Value": 54653}, {"Length": "93", "Height": "45", "Depth": "72", "Demand": 1, "DemandMax": null, "Value": 301320}, {"Length": "13", "Height": "39", "Depth": "44", "Demand": 1, "DemandMax": null, "Value": 22308}, {"Length": "57", "Height": "61", "Depth": "60", "Demand": 1, "DemandMax": null, "Value": 208620}, {"Length": "77", "Height": "90", "Depth": "98", "Demand": 1, "DemandMax": null, "Value": 679140}, {"Length": "91", "Height": "6", "Depth": "94", "Demand": 1, "DemandMax": null, "Value": 51324}, {"Length": "91", "Height": "38", "Depth": "86", "Demand": 1, "DemandMax": null, "Value": 297388}, {"Length": "86", "Height": "6", "Depth": "90", "Demand": 1, "DemandMax": null, "Value": 46440}, {"Length": "92", "Height": "33", "Depth": "86", "Demand": 1, "DemandMax": null, "Value": 261096}, {"Length": "92", "Height": "81", "Depth": "54", "Demand": 1, "DemandMax": null, "Value": 402408}, {"Length": "88", "Height": "41", "Depth": "95", "Demand": 1, "DemandMax": null, "Value": 342760}, {"Length": "69", "Height": "43", "Depth": "72", "Demand": 1, "DemandMax": null, "Value": 213624}, {"Length": "72", "Height": "47", "Depth": "93", "Demand": 1, "DemandMax": null, "Value": 314712}, {"Length": "63", "Height": "99", "Depth": "54", "Demand": 1, "DemandMax": null, "Value": 336798}, {"Length": "90", "Height": "32", "Depth": "92", "Demand": 1, "DemandMax": null, "Value": 264960}, {"Length": "30", "Height": "42", "Depth": "1", "Demand": 1, "DemandMax": null, "Value": 1260}, {"Length": "97", "Height": "38", "Depth": "72", "Demand": 1, "DemandMax": null, "Value": 265392}, {"Length": "39", "Height": "78", "Depth": "79", "Demand": 1, "DemandMax": null, "Value": 240318}, {"Length": "98", "Height": "1", "Depth": "79", "Demand": 1, "DemandMax": null, "Value": 7742}, {"Length": "68", "Height": "25", "Depth": "90", "Demand": 1, "DemandMax": null, "Value": 153000}, {"Length": "74", "Height": "5", "Depth": "78", "Demand": 1, "DemandMax": null, "Value": 28860}, {"Length": "79", "Height": "39", "Depth": "79", "Demand": 1, "DemandMax": null, "Value": 243399}, {"Length": "74", "Height": "14", "Depth": "81", "Demand": 1, "DemandMax": null, "Value": 83916}, {"Length": "78", "Height": "17", "Depth": "88", "Demand": 1, "DemandMax": null, "Value": 116688}, {"Length": "83", "Height": "67", "Depth": "48", "Demand": 1, "DemandMax": null, "Value": 266928}, {"Length": "29", "Height": "15", "Depth": "43", "Demand": 1, "DemandMax": null, "Value": 18705}, {"Length": "72", "Height": "27", "Depth": "97", "Demand": 1, "DemandMax": null, "Value": 188568}, {"Length": "86", "Height": "23", "Depth": "71", "Demand": 1, "DemandMax": null, "Value": 140438}, {"Length": "95", "Height": "27", "Depth": "95", "Demand": 1, "DemandMax": null, "Value": 243675}, {"Length": "80", "Height": "88", "Depth": "50", "Demand": 1, "DemandMax": null, "Value": 352000}, {"Length": "82", "Height": "22", "Depth": "67", "Demand": 1, "DemandMax": null, "Value": 120868}, {"Length": "100", "Height": "33", "Depth": "94", "Demand": 1, "DemandMax": null, "Value": 310200}, {"Length": "3", "Height": "98", "Depth": "82", "Demand": 1, "DemandMax": null, "Value": 24108}, {"Length": "92", "Height": "39", "Depth": "84", "Demand": 1, "DemandMax": null, "Value": 301392}, {"Length": "66", "Height": "79", "Depth": "45", "Demand": 1, "DemandMax": null, "Value": 234630}, {"Length": "70", "Height": "4", "Depth": "94", "Demand": 1, "DemandMax": null, "Value": 26320}, {"Length": "37", "Height": "86", "Depth": "78", "Demand": 1, "DemandMax": null, "Value": 248196}, {"Length": "67", "Height": "84", "Depth": "39", "Demand": 1, "DemandMax": null, "Value": 219492}, {"Length": "74", "Height": "31", "Depth": "67", "Demand": 1, "DemandMax": null, "Value": 153698}, {"Length": "18", "Height": "18", "Depth": "13", "Demand": 1, "DemandMax": null, "Value": 4212}, {"Length": "80", "Height": "4", "Depth": "81", "Demand": 1, "DemandMax": null, "Value": 25920}, {"Length": "70", "Height": "13", "Depth": "80", "Demand": 1, "DemandMax": null, "Value": 72800}, {"Length": "71", "Height": "1", "Depth": "100", "Demand": 1, "DemandMax": null, "Value": 7100}, {"Length": "8", "Height": "26", "Depth": "34", "Demand": 1, "DemandMax": null, "Value": 7072}, {"Length": "16", "Height": "72", "Depth": "74", "Demand": 1, "DemandMax": null, "Value": 85248}, {"Length": "78", "Height": "36", "Depth": "96", "Demand": 1, "DemandMax": null, "Value": 269568}, {"Length": "86", "Height": "75", "Depth": "34", "Demand": 1, "DemandMax": null, "Value": 219300}, {"Length": "12", "Height": "87", "Depth": "83", "Demand": 1, "DemandMax": null, "Value": 86652}, {"Length": "67", "Height": "91", "Depth": "62", "Demand": 1, "DemandMax": null, "Value": 378014}, {"Length": "71", "Height": "40", "Depth": "100", "Demand": 1, "DemandMax": null, "Value": 284000}, {"Length": "23", "Height": "12", "Depth": "11", "Demand": 1, "DemandMax": null, "Value": 3036}, {"Length": "74", "Height": "75", "Depth": "44", "Demand": 1, "DemandMax": null, "Value": 244200}, {"Length": "82", "Height": "1", "Depth": "78", "Demand": 1, "DemandMax": null, "Value": 6396}, {"Length": "77", "Height": "11", "Depth": "89", "Demand": 1, "DemandMax": null, "Value": 75383}, {"Length": "80", "Height": "6", "Depth": "99", "Demand": 1, "DemandMax": null, "Value": 47520}, {"Length": "82", "Height": "6", "Depth": "93", "Demand": 1, "DemandMax": null, "Value": 45756}, {"Length": "70", "Height": "40", "Depth": "67", "Demand": 1, "DemandMax": null, "Value": 187600}, {"Length": "28", "Height": "86", "Depth": "73", "Demand": 1, "DemandMax": null, "Value": 175784}, {"Length": "66", "Height": "12", "Depth": "66", "Demand": 1, "DemandMax": null, "Value": 52272}, {"Length": "80", "Height": "95", "Depth": "50", "Demand": 1, "DemandMax": null, "Value": 380000}, {"Length": "92", "Height": "29", "Depth": "100", "Demand": 1, "DemandMax": null, "Value": 266800}, {"Length": "73", "Height": "29", "Depth": "73", "Demand": 1, "DemandMax": null, "Value": 154541}, {"Length": "84", "Height": "34", "Depth": "78", "Demand": 1, "DemandMax": null, "Value": 222768}, {"Length": "71", "Height": "61", "Depth": "54", "Demand": 1, "DemandMax": null, "Value": 233874}, {"Length": "79", "Height": "36", "Depth": "82", "Demand": 1, "DemandMax": null, "Value": 233208}, {"Length": "68", "Height": "15", "Depth": "66", "Demand": 1, "DemandMax": null, "Value": 67320}, {"Length": "96", "Height": "7", "Depth": "85", "Demand": 1, "DemandMax": null, "Value": 57120}, {"Length": "87", "Height": "72", "Depth": "38", "Demand": 1, "DemandMax": null, "Value": 238032}, {"Length": "78", "Height": "34", "Depth": "84", "Demand": 1, "DemandMax": null, "Value": 222768}, {"Length": "72", "Height": "6", "Depth": "86", "Demand": 1, "DemandMax": null, "Value": 37152}, {"Length": "70", "Height": "7", "Depth": "88", "Demand": 1, "DemandMax": null, "Value": 43120}, {"Length": "86", "Height": "42", "Depth": "79", "Demand": 1, "DemandMax": null, "Value": 285348}, {"Length": "94", "Height": "6", "Depth": "92", "Demand": 1, "DemandMax": null, "Value": 51888}, {"Length": "44", "Height": "86", "Depth": "69", "Demand": 1, "DemandMax": null, "Value": 261096}, {"Length": "97", "Height": "16", "Depth": "79", "Demand": 1, "DemandMax": null, "Value": 122608}, {"Length": "68", "Height": "23", "Depth": "100", "Demand": 1, "DemandMax": null, "Value": 156400}, {"Length": "74", "Height": "77", "Depth": "32", "Demand": 1, "DemandMax": null, "Value": 182336}, {"Length": "69", "Height": "12", "Depth": "99", "Demand": 1, "DemandMax": null, "Value": 81972}, {"Length": "97", "Height": "33", "Depth": "73", "Demand": 1, "DemandMax": null, "Value": 233673}, {"Length": "98", "Height": "29", "Depth": "95", "Demand": 1, "DemandMax": null, "Value": 269990}, {"Length": "95", "Height": "45", "Depth": "72", "Demand": 1, "DemandMax": null, "Value": 307800}, {"Length": "81", "Height": "42", "Depth": "72", "Demand": 1, "DemandMax": null, "Value": 244944}, {"Length": "87", "Height": "67", "Depth": "28", "Demand": 1, "DemandMax": null, "Value": 163212}, {"Length": "90", "Height": "4", "Depth": "77", "Demand": 1, "DemandMax": null, "Value": 27720}, {"Length": "97", "Height": "92", "Depth": "33", "Demand": 1, "DemandMax": null, "Value": 294492}, {"Length": "78", "Height": "100", "Depth": "46", "Demand": 1, "DemandMax": null, "Value": 358800}, {"Length": "69", "Height": "8", "Depth": "98", "Demand": 1, "DemandMax": null, "Value": 54096}, {"Length": "77", "Height": "23", "Depth": "99", "Demand": 1, "DemandMax": null, "Value": 175329}, {"Length": "70", "Height": "60", "Depth": "62", "Demand": 1, "DemandMax": null, "Value": 260400}, {"Length": "88", "Height": "45", "Depth": "79", "Demand": 1, "DemandMax": null, "Value": 312840}, {"Length": "75", "Height": "72", "Depth": "7", "Demand": 1, "DemandMax": null, "Value": 37800}, {"Length": "4", "Height": "1", "Depth": "36", "Demand": 1, "DemandMax": null, "Value": 144}, {"Length": "83", "Height": "25", "Depth": "80", "Demand": 1, "DemandMax": null, "Value": 166000}, {"Length": "72", "Height": "27", "Depth": "98", "Demand": 1, "DemandMax": null, "Value": 190512}, {"Length": "93", "Height": "21", "Depth": "91", "Demand": 1, "DemandMax": null, "Value": 177723}, {"Length": "10", "Height": "76", "Depth": "88", "Demand": 1, "DemandMax": null, "Value": 66880}, {"Length": "66", "Height": "36", "Depth": "75", "Demand": 1, "DemandMax": null, "Value": 178200}, {"Length": "20", "Height": "12", "Depth": "38", "Demand": 1, "DemandMax": null, "Value": 9120}, {"Length": "93", "Height": "5", "Depth": "79", "Demand": 1, "DemandMax": null, "Value": 36735}, {"Length": "77", "Height": "67", "Depth": "29", "Demand": 1, "DemandMax": null, "Value": 149611}, {"Length": "66", "Height": "91", "Depth": "97", "Demand": 1, "DemandMax": null, "Value": 582582}]}