{"name": "2", "Objects": [{"Length": "100", "Height": "100", "Depth": "100", "Stock": null, "Cost": 1000000}], "Items": [{"Length": "31", "Height": "75", "Depth": "69", "Demand": 1, "DemandMax": null, "Value": 160425}, {"Length": "9", "Height": "36", "Depth": "11", "Demand": 1, "DemandMax": null, "Value": 3564}, {"Length": "68", "Height": "99", "Depth": "66", "Demand": 1, "DemandMax": null, "Value": 444312}, {"Length": "51", "Height": "85", "Depth": "78", "Demand": 1, "DemandMax": null, "Value": 338130}, {"Length": "82", "Height": "56", "Depth": "85", "Demand": 1, "DemandMax": null, "Value": 390320}, {"Length": "85", "Height": "81", "Depth": "26", "Demand": 1, "DemandMax": null, "Value": 179010}, {"Length": "73", "Height": "66", "Depth": "70", "Demand": 1, "DemandMax": null, "Value": 337260}, {"Length": "73", "Height": "8", "Depth": "83", "Demand": 1, "DemandMax": null, "Value": 48472}, {"Length": "97", "Height": "54", "Depth": "64", "Demand": 1, "DemandMax": null, "Value": 335232}, {"Length": "53", "Height": "67", "Depth": "89", "Demand": 1, "DemandMax": null, "Value": 316039}, {"Length": "88", "Height": "51", "Depth": "73", "Demand": 1, "DemandMax": null, "Value": 327624}, {"Length": "67", "Height": "76", "Depth": "3", "Demand": 1, "DemandMax": null, "Value": 15276}, {"Length": "82", "Height": "63", "Depth": "79", "Demand": 1, "DemandMax": null, "Value": 408114}, {"Length": "78", "Height": "93", "Depth": "9", "Demand": 1, "DemandMax": null, "Value": 65286}, {"Length": "66", "Height": "84", "Depth": "71", "Demand": 1, "DemandMax": null, "Value": 393624}, {"Length": "80", "Height": "69", "Depth": "78", "Demand": 1, "DemandMax": null, "Value": 430560}, {"Length": "86", "Height": "88", "Depth": "48", "Demand": 1, "DemandMax": null, "Value": 363264}, {"Length": "94", "Height": "66", "Depth": "53", "Demand": 1, "DemandMax": null, "Value": 328812}, {"Length": "8", "Height": "96", "Depth": "88", "Demand": 1, "DemandMax": null, "Value": 67584}, {"Length": "46", "Height": "83", "Depth": "72", "Demand": 1, "DemandMax": null, "Value": 274896}, {"Length": "63", "Height": "50", "Depth": "86", "Demand": 1, "DemandMax": null, "Value": 270900}, {"Length": "29", "Height": "84", "Depth": "99", "Demand": 1, "DemandMax": null, "Value": 241164}, {"Length": "69", "Height": "82", "Depth": "82", "Demand": 1, "DemandMax": null, "Value": 463956}, {"Length": "55", "Height": "52", "Depth": "92", "Demand": 1, "DemandMax": null, "Value": 263120}, {"Length": "84", "Height": "99", "Depth": "91", "Demand": 1, "DemandMax": null, "Value": 756756}, {"Length": "89", "Height": "75", "Depth": "60", "Demand": 1, "DemandMax": null, "Value": 400500}, {"Length": "52", "Height": "72", "Depth": "54", "Demand": 1, "DemandMax": null, "Value": 202176}, {"Length": "90", "Height": "65", "Depth": "72", "Demand": 1, "DemandMax": null, "Value": 421200}, {"Length": "67", "Height": "10", "Depth": "83", "Demand": 1, "DemandMax": null, "Value": 55610}, {"Length": "94", "Height": "78", "Depth": "53", "Demand": 1, "DemandMax": null, "Value": 388596}, {"Length": "54", "Height": "68", "Depth": "52", "Demand": 1, "DemandMax": null, "Value": 190944}, {"Length": "77", "Height": "95", "Depth": "54", "Demand": 1, "DemandMax": null, "Value": 395010}, {"Length": "16", "Height": "21", "Depth": "24", "Demand": 1, "DemandMax": null, "Value": 8064}, {"Length": "98", "Height": "63", "Depth": "97", "Demand": 1, "DemandMax": null, "Value": 598878}, {"Length": "54", "Height": "58", "Depth": "97", "Demand": 1, "DemandMax": null, "Value": 303804}, {"Length": "28", "Height": "39", "Depth": "14", "Demand": 1, "DemandMax": null, "Value": 15288}, {"Length": "14", "Height": "46", "Depth": "45", "Demand": 1, "DemandMax": null, "Value": 28980}, {"Length": "51", "Height": "69", "Depth": "94", "Demand": 1, "DemandMax": null, "Value": 330786}, {"Length": "51", "Height": "66", "Depth": "69", "Demand": 1, "DemandMax": null, "Value": 232254}, {"Length": "71", "Height": "89", "Depth": "99", "Demand": 1, "DemandMax": null, "Value": 625581}, {"Length": "28", "Height": "66", "Depth": "85", "Demand": 1, "DemandMax": null, "Value": 157080}, {"Length": "83", "Height": "75", "Depth": "86", "Demand": 1, "DemandMax": null, "Value": 535350}, {"Length": "85", "Height": "55", "Depth": "57", "Demand": 1, "DemandMax": null, "Value": 266475}, {"Length": "11", "Height": "39", "Depth": "12", "Demand": 1, "DemandMax": null, "Value": 5148}, {"Length": "71", "Height": "95", "Depth": "90", "Demand": 1, "DemandMax": null, "Value": 607050}, {"Length": "92", "Height": "10", "Depth": "76", "Demand": 1, "DemandMax": null, "Value": 69920}, {"Length": "70", "Height": "52", "Depth": "84", "Demand": 1, "DemandMax": null, "Value": 305760}, {"Length": "72", "Height": "87", "Depth": "85", "Demand": 1, "DemandMax": null, "Value": 532440}, {"Length": "91", "Height": "22", "Depth": "99", "Demand": 1, "DemandMax": null, "Value": 198198}, {"Length": "51", "Height": "84", "Depth": "61", "Demand": 1, "DemandMax": null, "Value": 261324}, {"Length": "54", "Height": "56", "Depth": "92", "Demand": 1, "DemandMax": null, "Value": 278208}, {"Length": "93", "Height": "80", "Depth": "88", "Demand": 1, "DemandMax": null, "Value": 654720}, {"Length": "70", "Height": "1", "Depth": "91", "Demand": 1, "DemandMax": null, "Value": 6370}, {"Length": "76", "Height": "65", "Depth": "73", "Demand": 1, "DemandMax": null, "Value": 360620}, {"Length": "72", "Height": "18", "Depth": "83", "Demand": 1, "DemandMax": null, "Value": 107568}, {"Length": "84", "Height": "88", "Depth": "55", "Demand": 1, "DemandMax": null, "Value": 406560}, {"Length": "54", "Height": "88", "Depth": "70", "Demand": 1, "DemandMax": null, "Value": 332640}, {"Length": "57", "Height": "61", "Depth": "58", "Demand": 1, "DemandMax": null, "Value": 201666}, {"Length": "98", "Height": "83", "Depth": "86", "Demand": 1, "DemandMax": null, "Value": 699524}, {"Length": "57", "Height": "86", "Depth": "93", "Demand": 1, "DemandMax": null, "Value": 455886}, {"Length": "29", "Height": "42", "Depth": "8", "Demand": 1, "DemandMax": null, "Value": 9744}, {"Length": "39", "Height": "76", "Depth": "83", "Demand": 1, "DemandMax": null, "Value": 246012}, {"Length": "98", "Height": "87", "Depth": "93", "Demand": 1, "DemandMax": null, "Value": 792918}, {"Length": "95", "Height": "65", "Depth": "56", "Demand": 1, "DemandMax": null, "Value": 345800}, {"Length": "58", "Height": "92", "Depth": "60", "Demand": 1, "DemandMax": null, "Value": 320160}, {"Length": "66", "Height": "78", "Depth": "20", "Demand": 1, "DemandMax": null, "Value": 102960}, {"Length": "96", "Height": "75", "Depth": "53", "Demand": 1, "DemandMax": null, "Value": 381600}, {"Length": "72", "Height": "37", "Depth": "72", "Demand": 1, "DemandMax": null, "Value": 191808}, {"Length": "89", "Height": "96", "Depth": "65", "Demand": 1, "DemandMax": null, "Value": 555360}, {"Length": "77", "Height": "81", "Depth": "7", "Demand": 1, "DemandMax": null, "Value": 43659}, {"Length": "63", "Height": "69", "Depth": "55", "Demand": 1, "DemandMax": null, "Value": 239085}, {"Length": "56", "Height": "61", "Depth": "79", "Demand": 1, "DemandMax": null, "Value": 269864}, {"Length": "50", "Height": "63", "Depth": "51", "Demand": 1, "DemandMax": null, "Value": 160650}, {"Length": "55", "Height": "73", "Depth": "76", "Demand": 1, "DemandMax": null, "Value": 305140}, {"Length": "97", "Height": "83", "Depth": "72", "Demand": 1, "DemandMax": null, "Value": 579672}, {"Length": "85", "Height": "57", "Depth": "51", "Demand": 1, "DemandMax": null, "Value": 247095}, {"Length": "82", "Height": "85", "Depth": "29", "Demand": 1, "DemandMax": null, "Value": 202130}, {"Length": "30", "Height": "80", "Depth": "96", "Demand": 1, "DemandMax": null, "Value": 230400}, {"Length": "55", "Height": "55", "Depth": "68", "Demand": 1, "DemandMax": null, "Value": 205700}, {"Length": "35", "Height": "80", "Depth": "80", "Demand": 1, "DemandMax": null, "Value": 224000}, {"Length": "61", "Height": "75", "Depth": "86", "Demand": 1, "DemandMax": null, "Value": 393450}, {"Length": "94", "Height": "74", "Depth": "67", "Demand": 1, "DemandMax": null, "Value": 466052}, {"Length": "65", "Height": "100", "Depth": "70", "Demand": 1, "DemandMax": null, "Value": 455000}, {"Length": "72", "Height": "98", "Depth": "51", "Demand": 1, "DemandMax": null, "Value": 359856}, {"Length": "64", "Height": "61", "Depth": "62", "Demand": 1, "DemandMax": null, "Value": 242048}, {"Length": "91", "Height": "69", "Depth": "95", "Demand": 1, "DemandMax": null, "Value": 596505}, {"Length": "72", "Height": "54", "Depth": "88", "Demand": 1, "DemandMax": null, "Value": 342144}, {"Length": "67", "Height": "26", "Depth": "82", "Demand": 1, "DemandMax": null, "Value": 142844}, {"Length": "77", "Height": "78", "Depth": "37", "Demand": 1, "DemandMax": null, "Value": 222222}, {"Length": "47", "Height": "66", "Depth": "76", "Demand": 1, "DemandMax": null, "Value": 235752}, {"Length": "76", "Height": "70", "Depth": "55", "Demand": 1, "DemandMax": null, "Value": 292600}, {"Length": "14", "Height": "41", "Depth": "4", "Demand": 1, "DemandMax": null, "Value": 2296}, {"Length": "83", "Height": "24", "Depth": "69", "Demand": 1, "DemandMax": null, "Value": 137448}, {"Length": "88", "Height": "97", "Depth": "77", "Demand": 1, "DemandMax": null, "Value": 657272}, {"Length": "73", "Height": "73", "Depth": "74", "Demand": 1, "DemandMax": null, "Value": 394346}, {"Length": "16", "Height": "48", "Depth": "15", "Demand": 1, "DemandMax": null, "Value": 11520}, {"Length": "88", "Height": "73", "Depth": "90", "Demand": 1, "DemandMax": null, "Value": 578160}, {"Length": "91", "Height": "53", "Depth": "57", "Demand": 1, "DemandMax": null, "Value": 274911}, {"Length": "16", "Height": "15", "Depth": "27", "Demand": 1, "DemandMax": null, "Value": 6480}, {"Length": "67", "Height": "61", "Depth": "55", "Demand": 1, "DemandMax": null, "Value": 224785}, {"Length": "74", "Height": "36", "Depth": "67", "Demand": 1, "DemandMax": null, "Value": 178488}, {"Length": "60", "Height": "90", "Depth": "95", "Demand": 1, "DemandMax": null, "Value": 513000}, {"Length": "98", "Height": "48", "Depth": "71", "Demand": 1, "DemandMax": null, "Value": 333984}, {"Length": "52", "Height": "100", "Depth": "78", "Demand": 1, "DemandMax": null, "Value": 405600}, {"Length": "97", "Height": "22", "Depth": "82", "Demand": 1, "DemandMax": null, "Value": 174988}, {"Length": "71", "Height": "67", "Depth": "32", "Demand": 1, "DemandMax": null, "Value": 152224}, {"Length": "66", "Height": "40", "Depth": "73", "Demand": 1, "DemandMax": null, "Value": 192720}, {"Length": "37", "Height": "80", "Depth": "73", "Demand": 1, "DemandMax": null, "Value": 216080}, {"Length": "70", "Height": "53", "Depth": "72", "Demand": 1, "DemandMax": null, "Value": 267120}, {"Length": "92", "Height": "3", "Depth": "76", "Demand": 1, "DemandMax": null, "Value": 20976}, {"Length": "99", "Height": "87", "Depth": "56", "Demand": 1, "DemandMax": null, "Value": 482328}, {"Length": "66", "Height": "53", "Depth": "92", "Demand": 1, "DemandMax": null, "Value": 321816}, {"Length": "14", "Height": "67", "Depth": "74", "Demand": 1, "DemandMax": null, "Value": 69412}, {"Length": "57", "Height": "83", "Depth": "76", "Demand": 1, "DemandMax": null, "Value": 359556}, {"Length": "58", "Height": "81", "Depth": "81", "Demand": 1, "DemandMax": null, "Value": 380538}, {"Length": "80", "Height": "64", "Depth": "89", "Demand": 1, "DemandMax": null, "Value": 455680}, {"Length": "63", "Height": "91", "Depth": "57", "Demand": 1, "DemandMax": null, "Value": 326781}, {"Length": "73", "Height": "61", "Depth": "74", "Demand": 1, "DemandMax": null, "Value": 329522}, {"Length": "82", "Height": "4", "Depth": "79", "Demand": 1, "DemandMax": null, "Value": 25912}, {"Length": "88", "Height": "89", "Depth": "95", "Demand": 1, "DemandMax": null, "Value": 744040}, {"Length": "91", "Height": "98", "Depth": "56", "Demand": 1, "DemandMax": null, "Value": 499408}, {"Length": "92", "Height": "59", "Depth": "69", "Demand": 1, "DemandMax": null, "Value": 374532}, {"Length": "90", "Height": "77", "Depth": "53", "Demand": 1, "DemandMax": null, "Value": 367290}, {"Length": "88", "Height": "82", "Depth": "57", "Demand": 1, "DemandMax": null, "Value": 411312}, {"Length": "74", "Height": "69", "Depth": "9", "Demand": 1, "DemandMax": null, "Value": 45954}, {"Length": "88", "Height": "36", "Depth": "69", "Demand": 1, "DemandMax": null, "Value": 218592}, {"Length": "68", "Height": "81", "Depth": "90", "Demand": 1, "DemandMax": null, "Value": 495720}, {"Length": "53", "Height": "76", "Depth": "63", "Demand": 1, "DemandMax": null, "Value": 253764}, {"Length": "83", "Height": "72", "Depth": "31", "Demand": 1, "DemandMax": null, "Value": 185256}, {"Length": "98", "Height": "59", "Depth": "55", "Demand": 1, "DemandMax": null, "Value": 318010}, {"Length": "76", "Height": "79", "Depth": "72", "Demand": 1, "DemandMax": null, "Value": 432288}, {"Length": "82", "Height": "55", "Depth": "71", "Demand": 1, "DemandMax": null, "Value": 320210}, {"Length": "80", "Height": "90", "Depth": "90", "Demand": 1, "DemandMax": null, "Value": 648000}, {"Length": "97", "Height": "90", "Depth": "50", "Demand": 1, "DemandMax": null, "Value": 436500}, {"Length": "61", "Height": "83", "Depth": "97", "Demand": 1, "DemandMax": null, "Value": 491111}, {"Length": "67", "Height": "97", "Depth": "89", "Demand": 1, "DemandMax": null, "Value": 578411}, {"Length": "3", "Height": "75", "Depth": "82", "Demand": 1, "DemandMax": null, "Value": 18450}, {"Length": "62", "Height": "70", "Depth": "81", "Demand": 1, "DemandMax": null, "Value": 351540}, {"Length": "74", "Height": "91", "Depth": "57", "Demand": 1, "DemandMax": null, "Value": 383838}, {"Length": "80", "Height": "58", "Depth": "81", "Demand": 1, "DemandMax": null, "Value": 375840}, {"Length": "73", "Height": "88", "Depth": "60", "Demand": 1, "DemandMax": null, "Value": 385440}, {"Length": "50", "Height": "77", "Depth": "84", "Demand": 1, "DemandMax": null, "Value": 323400}, {"Length": "75", "Height": "96", "Depth": "84", "Demand": 1, "DemandMax": null, "Value": 604800}, {"Length": "79", "Height": "20", "Depth": "91", "Demand": 1, "DemandMax": null, "Value": 143780}, {"Length": "82", "Height": "66", "Depth": "63", "Demand": 1, "DemandMax": null, "Value": 340956}, {"Length": "38", "Height": "15", "Depth": "26", "Demand": 1, "DemandMax": null, "Value": 14820}, {"Length": "60", "Height": "66", "Depth": "50", "Demand": 1, "DemandMax": null, "Value": 198000}, {"Length": "74", "Height": "44", "Depth": "91", "Demand": 1, "DemandMax": null, "Value": 296296}, {"Length": "93", "Height": "81", "Depth": "68", "Demand": 1, "DemandMax": null, "Value": 512244}, {"Length": "88", "Height": "98", "Depth": "74", "Demand": 1, "DemandMax": null, "Value": 638176}]}